{
  "os": "Linux-5.15.0-1091-nvidia-x86_64-with-glibc2.35",
  "python": "CPython 3.10.12",
  "startedAt": "2026-05-07T01:28:07.036870Z",
  "args": [
    "--kind",
    "both",
    "--device",
    "cpu",
    "--model_path",
    "/mnt/cepheid/users/hsypfsv/rtFIN_ISL_ML/embedding_tuning/h100_slurm/output/111677_20260506_114341_both_2gpu/bge",
    "--output_dir",
    "/mnt/cepheid/users/hsypfsv/rtFIN_ISL_ML/embedding_tuning/h100_slurm/benchmark_results/bge_all_cpu_wandb",
    "--batch_size",
    "32",
    "--qa_path",
    "/mnt/cepheid/users/hsypfsv/rtFIN_ISL_ML/embedding_tuning/h100_slurm/autorag_bench/data/qa_v4.parquet",
    "--corpus_path",
    "/mnt/cepheid/users/hsypfsv/rtFIN_ISL_ML/embedding_tuning/h100_slurm/autorag_bench/data/ocr_corpus_v3.parquet"
  ],
  "program": "/mnt/cepheid/users/hsypfsv/rtFIN_ISL_ML/embedding_tuning/h100_slurm/benchmark_korean_embeddings.py",
  "codePath": "benchmark_korean_embeddings.py",
  "codePathLocal": "benchmark_korean_embeddings.py",
  "email": "xianxie31@korea.ac.kr",
  "root": "/mnt/cepheid/users/hsypfsv/rtFIN_ISL_ML/embedding_tuning/h100_slurm",
  "host": "DGX-H100-11",
  "executable": "/usr/bin/python3",
  "cpu_count": 112,
  "cpu_count_logical": 224,
  "disk": {
    "/": {
      "total": "1888425144320",
      "used": "951026843648"
    }
  },
  "memory": {
    "total": "2164193984512"
  },
  "slurm": {
    "cluster_name": "deepops",
    "conf": "/etc/slurm/slurm.conf",
    "cpus_on_node": "8",
    "cpus_per_task": "8",
    "gtids": "0",
    "job_account": "idle_gpu",
    "job_cpus_per_node": "8",
    "job_end_time": "1809653276",
    "job_gid": "1061",
    "job_id": "111823",
    "job_name": "bge_bench_cpu_wandb",
    "job_nodelist": "DGX-H100-11",
    "job_num_nodes": "1",
    "job_partition": "h100",
    "job_qos": "normal",
    "job_start_time": "1778117276",
    "job_uid": "1061",
    "job_user": "hsypfsv",
    "jobid": "111823",
    "localid": "0",
    "mem_per_node": "49152",
    "nnodes": "1",
    "node_aliases": "(null)",
    "nodeid": "0",
    "nodelist": "DGX-H100-11",
    "prio_process": "0",
    "procid": "0",
    "submit_dir": "/mnt/cepheid/users/hsypfsv/rtFIN_ISL_ML/embedding_tuning/h100_slurm",
    "submit_host": "login-1",
    "task_pid": "2462582",
    "tasks_per_node": "1",
    "topology_addr": "DGX-H100-11",
    "topology_addr_pattern": "node",
    "working_cluster": "deepops:login-1:6717:9984:109"
  },
  "writerId": "go8j7ltyqecl96a189yvdlenieuyx9qx"
}